[
  {
    "id": "2070607285957677279",
    "text": "RT @j0xnah: the Polymarket us ramp is quite absurd\n\nweekly fees: ~$1m -&gt; $8.3m\n\n~$42m collected since march\n\nand @Polymarket still hasn't s…",
    "created_at": "Fri Jun 26 20:37:01 +0000 2026",
    "handle": "j0xnah",
    "source": "unofficial_x"
  },
  {
    "id": "2070541334679577076",
    "text": "the Polymarket us ramp is quite absurd\n\nweekly fees: ~$1m -&gt; $8.3m\n\n~$42m collected since march\n\nand @Polymarket still hasn't shipped a desktop app https://t.co/eyCza1xVL6",
    "created_at": "Fri Jun 26 16:14:57 +0000 2026",
    "handle": "j0xnah",
    "source": "unofficial_x"
  },
  {
    "id": "2070244267822350355",
    "text": "RT @wronguser000: Unfortunately and not that i care about another grown man financial situation but it does seem like eventually Saylor has…",
    "created_at": "Thu Jun 25 20:34:31 +0000 2026",
    "handle": "j0xnah",
    "source": "unofficial_x"
  },
  {
    "id": "2070150994890043752",
    "text": "did I need this? absolutely. https://t.co/UpUTVoUywP",
    "created_at": "Thu Jun 25 14:23:53 +0000 2026",
    "handle": "j0xnah",
    "source": "unofficial_x"
  },
  {
    "id": "2069891078354792770",
    "text": "burger money for the week on @Polymarket \n\nthank you to the goats Vargas and Manzambi https://t.co/csm9rJFcuB",
    "created_at": "Wed Jun 24 21:11:04 +0000 2026",
    "handle": "j0xnah",
    "source": "unofficial_x"
  },
  {
    "id": "2069509919913464076",
    "text": "RT @Polymarket: Questions are everything. \n\nBecause the people who never stop asking are the ones who find answers. https://t.co/MZteQLEfqQ",
    "created_at": "Tue Jun 23 19:56:29 +0000 2026",
    "handle": "j0xnah",
    "source": "unofficial_x"
  },
  {
    "id": "2069340174585102714",
    "text": "RT @j0xnah: the whole \"Does @Polymarket Have a Token?\" site update conversation is kinda funny\n\nit's a carefully worded disclaimer that sup…",
    "created_at": "Tue Jun 23 08:41:58 +0000 2026",
    "handle": "j0xnah",
    "source": "unofficial_x"
  },
  {
    "id": "2069186654145753119",
    "text": "the whole \"Does @Polymarket Have a Token?\" site update conversation is kinda funny\n\nit's a carefully worded disclaimer that suppresses scams and confirms nothing. \"has not announced plans\" ≠ \"no plans\"\n\ncalm down frens https://t.co/F9LGTQOpzi",
    "created_at": "Mon Jun 22 22:31:56 +0000 2026",
    "handle": "j0xnah",
    "source": "unofficial_x"
  },
  {
    "id": "2068405698547839276",
    "text": "forgot to share my @Polymarket combo today\n\nfirst leg already hit, onto the next. https://t.co/0EqOgCNngP",
    "created_at": "Sat Jun 20 18:48:42 +0000 2026",
    "handle": "j0xnah",
    "source": "unofficial_x"
  },
  {
    "id": "2067968034388512874",
    "text": "another day, another @Polymarket combo\n\ngood luck! https://t.co/N4Tea8cUtg",
    "created_at": "Fri Jun 19 13:49:35 +0000 2026",
    "handle": "j0xnah",
    "source": "unofficial_x"
  },
  {
    "id": "2067713600672682013",
    "text": "Manzambi the fucking GOAT\n\nwhat a game https://t.co/KVQtoD9E0p",
    "created_at": "Thu Jun 18 20:58:33 +0000 2026",
    "handle": "j0xnah",
    "source": "unofficial_x"
  },
  {
    "id": "2067645654193639457",
    "text": "little @Polymarket combo for my birthday\n\nwish me luck, I'm going to celebrate a bit now https://t.co/LPKOEDk87Y",
    "created_at": "Thu Jun 18 16:28:33 +0000 2026",
    "handle": "j0xnah",
    "source": "unofficial_x"
  },
  {
    "id": "2067508942016536845",
    "text": "A year ago I was 20, broke, lost, confused, hopeless and in a constant state of anxiety.\n\nNow I‘m 21🥳🎂 https://t.co/yJy7rOlzfN",
    "created_at": "Thu Jun 18 07:25:18 +0000 2026",
    "handle": "j0xnah",
    "source": "unofficial_x"
  },
  {
    "id": "2067322676830409003",
    "text": "Penaldo is deadass a liability for Portugal https://t.co/uj9M8bJF8K",
    "created_at": "Wed Jun 17 19:05:09 +0000 2026",
    "handle": "j0xnah",
    "source": "unofficial_x"
  },
  {
    "id": "2067284197794882043",
    "text": "congrats @shayne_coplan on 6 years\n\n@Polymarket is the reason I started writing more and found people worth writing for. grateful to be even a small part of this\n\nhere's to what's next🥂 https://t.co/dZWZFvVcfg",
    "created_at": "Wed Jun 17 16:32:15 +0000 2026",
    "handle": "j0xnah",
    "source": "unofficial_x"
  },
  {
    "id": "2067270034586562638",
    "text": "another @Polymarket combo for today (last one)\n\ntrailing a friend here, let's see how we do https://t.co/TG5bJqsjcK",
    "created_at": "Wed Jun 17 15:35:58 +0000 2026",
    "handle": "j0xnah",
    "source": "unofficial_x"
  },
  {
    "id": "2067225482358091786",
    "text": "built another three leg combo on @Polymarket \n\nfeeling fairly confident about this one https://t.co/gBX7JnQ4xu",
    "created_at": "Wed Jun 17 12:38:56 +0000 2026",
    "handle": "j0xnah",
    "source": "unofficial_x"
  },
  {
    "id": "2066878543414313270",
    "text": "I just bought some buuuuullshit😭😭 https://t.co/1Dey6JZb7p",
    "created_at": "Tue Jun 16 13:40:20 +0000 2026",
    "handle": "j0xnah",
    "source": "unofficial_x"
  },
  {
    "id": "2066581456445440291",
    "text": "spanish strikers today https://t.co/TxInC8oGDQ",
    "created_at": "Mon Jun 15 17:59:49 +0000 2026",
    "handle": "j0xnah",
    "source": "unofficial_x"
  },
  {
    "id": "2066279211841597858",
    "text": "https://t.co/LqpI8OzImu",
    "created_at": "Sun Jun 14 21:58:48 +0000 2026",
    "handle": "j0xnah",
    "source": "unofficial_x"
  }
]